[
  {
    "ClassIndex": -3,
    "InstanceName": null,
    "ClassName": "WMFile",
    "SuperIndex": 0,
    "Package": "0x0",
    "ObjectNameIndex": 9,
    "ObjectName": "WeaponManager",
    "Flag": "0xF0004",
    "SerialSizeIndex": 242715,
    "SerialOffsetIndex": 192,
    "SerialOffsetIndexString": null
  },
  {
    "ClassIndex": -2,
    "InstanceName": null,
    "ClassName": "GMFile",
    "SuperIndex": 0,
    "Package": "0x0",
    "ObjectNameIndex": 8,
    "ObjectName": "GameManager",
    "Flag": "0xF0004",
    "SerialSizeIndex": 666328,
    "SerialOffsetIndex": 242907,
    "SerialOffsetIndexString": null
  }
]